image_detection_core/__init__.py
image_detection_core/constants.py
image_detection_core/save_model.py
image_detection_core/service/object_detection_service.py
image_detection_core/utils.py
image_detection_core/version.py
image_detection_core/yolo/backbone.py
image_detection_core/yolo/common.py
image_detection_core/yolo/config.py
image_detection_core/yolo/dataset.py
image_detection_core/yolo/functions.py
image_detection_core/yolo/utils.py
image_detection_core/yolo/yolov4.py
image_detection_core-0.6.0.dist-info/LICENSE.txt
image_detection_core-0.6.0.dist-info/WHEEL
image_detection_core-0.6.0.dist-info/METADATA
image_detection_core-0.6.0.dist-info/RECORD
